partnext/__init__.py
partnext/dataset.py
partnext/io.py
partnext/object.py
partnext/utils.py
partnext-1.0.1.dist-info/licenses/LICENSE
partnext-1.0.1.dist-info/METADATA
partnext-1.0.1.dist-info/WHEEL
partnext-1.0.1.dist-info/top_level.txt
partnext-1.0.1.dist-info/RECORD
