Metadata-Version: 2.4
Name: partnext
Version: 1.0.1
Summary: Dataset toolkit for using PartNeXt dataset
Home-page: https://github.com/AuthorityWang/PartNeXt
Author: AuthorityWang
Author-email: wangph12025@shanghaitech.edu.cn
License-File: LICENSE
Requires-Dist: trimesh
Requires-Dist: datasets
Requires-Dist: numpy
Dynamic: author
Dynamic: author-email
Dynamic: description
Dynamic: description-content-type
Dynamic: home-page
Dynamic: license-file
Dynamic: requires-dist
Dynamic: summary
